{
  "santos": [
    {
      "id": "2",
      "name": "Shiryu",
      "constellation": "Dragón"
    },
    {
      "id": "3",
      "name": "Hyoga",
      "constellation": "Cisne"
    },
    {
      "id": "4",
      "name": "Shun",
      "constellation": "Andrómeda"
    },
    {
      "id": "5",
      "name": "Ikki",
      "constellation": "Fénix"
    },
    {
      "id": "1710994217122",
      "name": "Aldebarán",
      "constellation": "Tauro"
    },
    {
      "id": "1710995114243",
      "name": "Saga",
      "constellation": "Geminis"
    },
    {
      "id": "1710996098451",
      "name": "Mu",
      "constellation": "Aries"
    }
  ]
}